odoo10_addon_account_due_list_aging_comments-10.0.1.0.0.99.dev4-py2.7-nspkg.pth
odoo/addons/account_due_list_aging_comments/README.rst
odoo/addons/account_due_list_aging_comments/__init__.py
odoo/addons/account_due_list_aging_comments/__manifest__.py
odoo/addons/account_due_list_aging_comments/i18n/account_due_list_aging_comments.pot
odoo/addons/account_due_list_aging_comments/i18n/de.po
odoo/addons/account_due_list_aging_comments/i18n/es.po
odoo/addons/account_due_list_aging_comments/i18n/it.po
odoo/addons/account_due_list_aging_comments/i18n/pt.po
odoo/addons/account_due_list_aging_comments/i18n/pt_BR.po
odoo/addons/account_due_list_aging_comments/i18n/sl.po
odoo/addons/account_due_list_aging_comments/models/__init__.py
odoo/addons/account_due_list_aging_comments/models/account_move_line.py
odoo/addons/account_due_list_aging_comments/static/description/icon.png
odoo/addons/account_due_list_aging_comments/views/payment_view.xml
odoo10_addon_account_due_list_aging_comments-10.0.1.0.0.99.dev4.dist-info/METADATA
odoo10_addon_account_due_list_aging_comments-10.0.1.0.0.99.dev4.dist-info/RECORD
odoo10_addon_account_due_list_aging_comments-10.0.1.0.0.99.dev4.dist-info/WHEEL
odoo10_addon_account_due_list_aging_comments-10.0.1.0.0.99.dev4.dist-info/namespace_packages.txt
odoo10_addon_account_due_list_aging_comments-10.0.1.0.0.99.dev4.dist-info/top_level.txt
